[
  {
    "id": "blog_1760019220817_p9lmrxt7h",
    "title": "Investments in Edelsteine",
    "slug": "investments-in-edelsteine",
    "excerpt": "Investments in Edelsteine - Ein Leitfaden zur Minimierung von Risiken",
    "content": "# Investment‑Edelsteine: Chancen, Risiken und MiFID‑II‑Hinweise\n*Stand: 2025-10-08*\n\n> **Wichtiger Hinweis (keine Anlageberatung):** Dieses Dokument ist **sachliche Information** zu Investment‑Edelsteinen und zur Orientierung an MiFID‑II‑Standards. Es ist **keine persönliche Empfehlung**. Für eine Empfehlung wären u. a. eine Geeignetheits-/Angemessenheitsprüfung, umfassende Kostentransparenz und Dokumentation erforderlich.\n\n---\n\n## Executive Summary\n- **Edelsteine als Anlage** können zur **Diversifikation** beitragen und sind **physische Sachwerte** mit hohem Wert pro Volumen. Gleichzeitig sind sie **illiquide**, **bewertungsintensiv** und **kostenpflichtig** in Verwahrung/Versicherung.  \n- **Marktdaten:** Der Knight Frank Luxury Investment Index (KFLII) weist für 2024 eine **12‑Monats‑Veränderung von –3,3 %** aus; **Schmuck +2,3 %**, **farbige Diamanten –2,2 %**; **10‑Jahres‑Werte**: Schmuck **+33,5 %**, farbige Diamanten **+3,8 %**. (Quelle: Wealth Report 2025)  \n- **Fancy‑Color‑Diamanten:** Laut FCRF setzte sich der **Preisrückgang** im **Q2/2025 (–0,5 %)** fort.  \n- **MiFID‑II‑Kontext:** MiFID II regelt **persönliche Empfehlungen zu Finanzinstrumenten**. Edelsteine sind **Sachwerte** (keine Finanzinstrumente), dennoch bieten sich **MiFID‑konforme Standards** (Geeignetheit, Kostentransparenz, Interessenkonflikte) als **Best Practice** an.\n\n---\n\n## 1) MiFID‑II‑Rahmen – was ist relevant?\nMiFID II definiert **Anlageberatung** als eine **persönliche Empfehlung** an einen Kunden **bezüglich eines oder mehrerer Geschäfte mit Finanzinstrumenten** ([MiFID II, Art. 4 Abs. 1 Nr. 4](https://eur-lex.europa.eu/legal-content/EN/TXT/PDF/?uri=CELEX%3A02014L0065-20230323)). Edelsteine sind **keine Finanzinstrumente**. Wenn jedoch regulierte Institute beraten, ist es sinnvoll, sich **an MiFID‑Standards zu orientieren**:\n\n- **Geeignetheit („Suitability“) & Dokumentation:** Firmen müssen Informationen zu **Kenntnissen/Erfahrungen**, **finanzieller Situation** (inkl. Verlusttragfähigkeit) und **Anlagezielen** (inkl. Risikotoleranz) erheben und Empfehlungen **dokumentieren** ([ESMA‑Leitlinien 2023, DE](https://www.esma.europa.eu/sites/default/files/2023-04/ESMA35-43-3172_Guidelines_on_certain_aspects_of_the_MiFID_II_suitability_requirements_DE.pdf)).  \n- **Rechtsgrundlagen der Geeignetheit:** Art. 25(2) MiFID II i. V. m. **Art. 54/55 Delegierte VO 2017/565** (Einzelheiten zur Geeignetheitsprüfung und Geeignetheitserklärung) — [EUR‑Lex 2017/565](https://eur-lex.europa.eu/eli/reg_del/2017/565/oj/eng).  \n- **Nachhaltigkeitspräferenzen:** Seit 2021 müssen **Sustainability Preferences** in die Geeignetheit einbezogen werden — [Delegierte VO (EU) 2021/1253](https://eur-lex.europa.eu/eli/reg_del/2021/1253/oj/eng).  \n- **Transparenz & Interessenkonflikte:** Kosten/Entgelte sind **klar offenzulegen**; **Anreize/Inducements** und **Interessenkonflikte** sind zu steuern bzw. offenzulegen (MiFID‑/Delegierte Rechtsakte; vgl. auch ESMA‑Leitlinien).\n\n> **Praktischer Schluss:** Auch wenn **MiFID II nicht unmittelbar** für Sachwerte wie Edelsteine gilt, ist es **sinnvoll**, Beratung und Dokumentation **analog** zu gestalten (Geeignetheitsprofil, Kostentransparenz, Risikoaufklärung).\n\n---\n\n## 2) Marktüberblick & Daten\n\n### 2.1 Knight Frank Luxury Investment Index (KFLII) — Q4/2024\nDer **Wealth Report 2025** zeigt für den KFLII: **–3,3 %** (12 Monate). Auszug der Teilindizes (12 Monate / 5 Jahre / 10 Jahre):  \n- **Schmuck:** **+2,3 % / +20,2 % / +33,5 %**  \n- **Farbige Diamanten:** **–2,2 % / +4,8 % / +3,8 %**  \n(Quelle mit Tabelle: *Knight Frank Wealth Report 2025, „The great luxury correction“, S. 70* — [PDF](https://www.dmproperties.com/wp-content/uploads/media/knight-frank-wealth-report-2025.pdf))\n\n**Einordnung:** Der Langfrist‑Zuwachs in **Schmuck** ist moderat, **farbige Diamanten** zeigen **schwache 10‑Jahres‑Werte**. Top‑Ergebnisse einzelner Auktionen sind **Ausnahmen** und **nicht** repräsentativ für den breiten Markt.\n\n### 2.2 Fancy Color Research Foundation (FCRF) — 2025\nDie **Fancy Color Diamond Index**‑Mitteilung für **Q2/2025** meldet **–0,5 %** (fünfter Rückgang in Folge; leichte Abkühlung des Marktes) — [FCRF Pressemitteilung 25.07.2025](https://www.fcresearch.org/press-releases/).\n\n---\n\n## 3) Vorteile von Investment‑Edelsteinen\n1. **Diversifikation & „Wearable Wealth“**: Ergänzung zu Finanzanlagen; physischer Sachwert, hoher Wert auf kleinem Volumen. (Marktumfeld: Wealth Report 2025, KFLII‑Segment „Jewellery“ — s. o.)  \n2. **Langfrist‑Potenzial bei Top‑Qualität**: Seltene, **unbehandelte** Steine mit nachvollziehbarer Herkunft können **Preispremien** erzielen. **Unabhängige Labore** (z. B. GIA) bestätigen Qualität/Behandlungen — wichtig für Marktakzeptanz.  \n   - GIA erklärt, dass **Behandlungen** den **Wert** beeinflussen und **offenzulegen** sind ([GIA: Einf. in Edelstein‑Behandlungen](https://www.gia.edu/gem-treatment)).  \n   - Für hochwertige Saphire/Rubine kann **„no evidence of heat“** den Wert **erhöhen** ([GIA FAQ Saphir‑Erwärmung](https://www.gia.edu/gia-faq-heat-treatment-affect-sapphire-value), [GIA FAQ Rubin‑Behandlungen](https://www.gia.edu/gia-faq-heat-treatment-ruby)).  \n3. **Internationale Nachfrage & Auktionsmärkte**: Für Spitzenstücke existieren globale Sekundärmärkte (Christie’s, Sotheby’s etc.); Preise sind jedoch **objekt‑ und timing‑abhängig**.\n\n---\n\n## 4) Zentrale Nachteile / Risiken\n1. **Illiquidität & Preisspannen**: Verkauf kann **Zeit** brauchen; **Preisbildung intransparent** und **heterogen** (Qualität, Behandlung, Herkunft, Seltenheit).  \n   - IGS betont die **Markt‑/Liquiditätsrisiken** und die Herausforderungen der **Preisfindung** ([IGS Risiko‑Management](https://www.gemsociety.org/article/risk-management-gemstone-investing/), [IGS Preisbildung](https://www.gemsociety.org/article/insights-on-gemstone-pricing/)).  \n2. **Bewertungs‑ & Echtheitsrisiken**: Ohne **unabhängige Gutachten** besteht Fehlkaufgefahr.  \n   - **GIA‑Berichte** sind **Qualitätsaussagen**, **keine** Wertgutachten, aber **marktakzeptiert** für Identität/Behandlungen/ggf. Herkunft ([GIA „Why GIA“](https://www.gia.edu/gem-lab/why-gia-grading), [GIA Value‑Factors‑Paper](https://www.gia.edu/doc/Value-Factors-Design-Cut-Quality-Colored-Gemstones-Gem-Market-News-GIA.pdf)).  \n3. **Marktzyklen**: Daten zeigen **Rückgänge** (z. B. FCRF 2025; KFLII 2024). Einzelfallauktionen widerspiegeln **nicht** den Gesamtmarkt. ([FCRF](https://www.fcresearch.org/press-releases/), [Wealth Report 2025](https://www.dmproperties.com/wp-content/uploads/media/knight-frank-wealth-report-2025.pdf))  \n4. **Kosten & Sicherheit**: Zertifizierung, Transport, **Versicherung** und **sichere Verwahrung** verursachen laufende Kosten; Diebstahl-/Verlust‑Risiko bleibt. (Allgemeine Risikohinweise; konkrete Tarife sind versicherungs‑/anbieterabhängig.)\n\n---\n\n## 5) MiFID‑II‑konforme Einordnung (Best‑Practice für Sachwerte)\n> **Ziel:** Auch ohne unmittelbare MiFID‑Pflicht für Edelsteine **Anlegerschutz‑Standards** anwenden.\n\n**Kernprinzipien (analog MiFID II):**\n- **Geeignetheit/Suitability** dokumentieren: Ziele, Horizont, **Liquiditätsbedarf**, Risikotoleranz, Verlusttragfähigkeit, Kenntnisse/Erfahrungen (vgl. [ESMA‑Leitlinien 2023, DE](https://www.esma.europa.eu/sites/default/files/2023-04/ESMA35-43-3172_Guidelines_on_certain_aspects_of_the_MiFID_II_suitability_requirements_DE.pdf); [2017/565, Art. 54/55](https://eur-lex.europa.eu/eli/reg_del/2017/565/oj/eng)).  \n- **Nachhaltigkeitspräferenzen** (falls gewünscht) dokumentieren: [2021/1253](https://eur-lex.europa.eu/eli/reg_del/2021/1253/oj/eng).  \n- **Kosten/gebühren** offenlegen: Kaufaufschläge, Zertifikate/Labore, Versicherung, Verwahrung, **Verkaufskosten** (Auktions‑/Händlerprovisionen, Versand).  \n- **Interessenkonflikte** adressieren: Keine unzulässigen Anreize; Offenlegung etwaiger **Eigenbestände**/Vergütungen.  \n- **Risikoaufklärung**: Illiquidität, Bewertungsunsicherheit, mögliche **Wertverluste**; keine Renditeversprechen.  \n- **Dokumentation**: Gesprächsprotokoll/Suitability‑Begründung, Nachweise (Laborberichte, Fotos, Rechnungen, Herkunftspapiere).\n\n---\n\n## 6) Praxis‑Checkliste für den Kauf (ohne Empfehlung)\n1. **Qualität belegen**: Unabhängige **Laborberichte** (z. B. GIA; ggf. Herkunftsbericht). [GIA: Why GIA](https://www.gia.edu/gem-lab/why-gia-grading)  \n2. **Behandlungen prüfen**: **Offenlegung** (z. B. Wärmebehandlung bei Saphir/Rubin). [GIA Behandlungen](https://www.gia.edu/gem-treatment), [GIA FAQ Saphir](https://www.gia.edu/gia-faq-heat-treatment-affect-sapphire-value)  \n3. **Preisrecherche & Spannen**: Marktpreise vergleichen; Intransparenz einkalkulieren. [IGS Preisbildung](https://www.gemsociety.org/article/insights-on-gemstone-pricing/)  \n4. **Kosten kalkulieren**: Zertifikat, Transport/Zoll, Versicherung, Verwahrung, künftige **Verkaufskosten**.  \n5. **Liquiditätsbedarf prüfen**: Nur mit **langem Horizont** und ohne kurzfristige Verkaufsnotwendigkeit.  \n6. **Diversifikation**: Max. als **Beimischung** eines breit gestreuten Portfolios.  \n7. **Dokumentation**: Kaufbelege, Fotos, Serien‑/Report‑Nummern, Sicherheitskonzept (Safe/Versicherung).  \n\n---\n\n## Quellen (Auswahl, Primär‑/Fachquellen)\n1. **ESMA (2023):** *Leitlinien zu einigen Aspekten der MiFID‑II‑Anforderungen an die Geeignetheit (DE)* — https://www.esma.europa.eu/sites/default/files/2023-04/ESMA35-43-3172_Guidelines_on_certain_aspects_of_the_MiFID_II_suitability_requirements_DE.pdf  \n2. **ESMA (2023):** *Guidelines on certain aspects of the MiFID II suitability requirements (EN)* — https://www.esma.europa.eu/sites/default/files/2023-04/ESMA35-43-3172_Guidelines_on_certain_aspects_of_the_MiFID_II_suitability_requirements.pdf  \n3. **EUR‑Lex:** *MiFID II – konsolidierte Fassung (Art. 4 Abs. 1 Nr. 4 Definition „investment advice“)* — https://eur-lex.europa.eu/legal-content/EN/TXT/PDF/?uri=CELEX%3A02014L0065-20230323  \n4. **EUR‑Lex:** *Delegated Regulation (EU) 2017/565* (u. a. Art. 54/55 Geeignetheit) — https://eur-lex.europa.eu/eli/reg_del/2017/565/oj/eng  \n5. **EUR‑Lex:** *Delegated Regulation (EU) 2021/1253* (Nachhaltigkeitspräferenzen in Suitability) — https://eur-lex.europa.eu/eli/reg_del/2021/1253/oj/eng  \n6. **Knight Frank (2025):** *The Wealth Report 2025* (KFLII‑Tabelle, S. 70) — https://www.dmproperties.com/wp-content/uploads/media/knight-frank-wealth-report-2025.pdf  \n7. **FCRF (2025):** *Press Release Q2/2025* — https://www.fcresearch.org/press-releases/  \n8. **GIA:** *An Introduction to Gem Treatments* — https://www.gia.edu/gem-treatment  \n9. **GIA:** *How does heat treatment affect a sapphire’s value?* — https://www.gia.edu/gia-faq-heat-treatment-affect-sapphire-value  \n10. **GIA:** *Does heat treatment affect the value of ruby?* — https://www.gia.edu/gia-faq-heat-treatment-ruby  \n11. **GIA:** *Why turn to GIA for gem grading and analysis?* — https://www.gia.edu/gem-lab/why-gia-grading  \n12. **GIA:** *Value factors & origin (PDF)* — https://www.gia.edu/doc/Value-Factors-Design-Cut-Quality-Colored-Gemstones-Gem-Market-News-GIA.pdf  \n13. **International Gem Society (IGS):** *Risk Management & Gemstone Investing* — https://www.gemsociety.org/article/risk-management-gemstone-investing/  \n14. **International Gem Society (IGS):** *Insights on Gemstone Pricing* — https://www.gemsociety.org/article/insights-on-gemstone-pricing/\n\n---\n\n\n",
    "author": "Gemilike Team",
    "category": "Investment",
    "tags": [],
    "image": "/uploads/stories/story-1760021191445.jpg",
    "published": true,
    "featured": false,
    "createdAt": "2025-10-09T14:13:40.817Z",
    "updatedAt": "2025-10-10T14:22:45.852Z",
    "publishedAt": "2025-10-10T14:22:45.852Z"
  },
  {
    "id": "blog_1760126235547_vx0c2sz12",
    "title": "Magnetismus in Edelsteinen",
    "slug": "magnetismus-in-edelsteinen",
    "excerpt": "Was ist Magnetismus in Edelsteinen",
    "content": "# 🧲 Magnetismus in Edelsteinen\n\n## 1. Grundlagen\n\n### 1.1 Physikalische Basis\nMagnetismus in Edelsteinen entsteht durch **ungepaarte Elektronen in den d-Orbitalen von Übergangsmetallionen**. Diese Elektronen erzeugen ein magnetisches Moment, das mit einem äußeren Magnetfeld wechselwirkt.  \n\nDie Stärke dieser Wechselwirkung wird durch die **magnetische Suszeptibilität (χ)** beschrieben – sie ist ein Maß für die *Anfälligkeit* eines Materials, magnetisiert zu werden.\n\n---\n\n## 2. Magnetische Suszeptibilität (χ)\n\n### 2.1 Definition\nDie **magnetische Suszeptibilität χ** ist eine dimensionslose Größe, die das Verhältnis der Magnetisierung \\( M \\) eines Materials zur angelegten magnetischen Feldstärke \\( H \\) beschreibt:\n\n\\[\n\\chi = \\frac{M}{H}\n\\]\n\n- **χ > 0:** Der Stoff ist *paramagnetisch* (anziehend).  \n- **χ < 0:** Der Stoff ist *diamagnetisch* (abstoßend).  \n\nFür Edelsteine sind typische Werte sehr klein (im Bereich von \\( 10^{-6} \\) bis \\( 10^{-3} \\)).\n\n---\n\n### 2.2 Typische χ-Werte bei Edelsteinen\n\n| Edelstein | χ (SI) | Verhalten |\n|------------|---------|------------|\n| Magnetit | > 1 | ferromagnetisch |\n| Hämatit | ~10⁻³ | stark paramagnetisch |\n| Almandin (Fe-Garnet) | 3×10⁻⁴ | stark paramagnetisch |\n| Spessartin | 1×10⁻⁴ | mittel |\n| Peridot | 5×10⁻⁵ | mittel |\n| Turmalin (Schörl) | 3×10⁻⁵ | schwach bis mittel |\n| Aquamarin | 1×10⁻⁶ | schwach |\n| Quarz | –1×10⁻⁶ | diamagnetisch |\n| Diamant | –2×10⁻⁶ | diamagnetisch |\n\nDiese Werte variieren je nach chemischer Zusammensetzung und Spurenelementgehalt stark.  \nEisen und Mangan erhöhen χ deutlich, während reine Al₂O₃- oder SiO₂-Phasen fast diamagnetisch sind.\n\n---\n\n## 3. Messverfahren\n\n### 3.1 Neodym-Magnet-Test (praktisch, gemmologisch)\nEin einfaches, qualitatives Verfahren mit einem starken **Neodym-Magneten (N52, ~10 000 G)**.  \n\n**Interpretation:**\n- Starke Bewegung → hoher χ-Wert (paramagnetisch)  \n- Keine Bewegung → χ nahe 0 oder negativ (diamagnetisch)\n\n---\n\n### 3.2 Quantitative Verfahren\n\n#### 3.2.1 Guoy-Waage\n- Klassisches Laborverfahren.  \n- Die Probe hängt in einem inhomogenen Magnetfeld, und die Gewichtsdifferenz (Magnetkraft) wird gemessen.  \n- Die magnetische Suszeptibilität ergibt sich aus:\n\n\\[\n\\chi = \\frac{2g \\Delta m}{H^2 A}\n\\]\n\nwobei  \nΔm = Gewichtsdifferenz,  \nH = Magnetfeldstärke,  \nA = Querschnittsfläche der Probe,  \ng = Erdbeschleunigung.\n\n➡️ **Nachteil:** Proben müssen pulverisiert werden → nicht zerstörungsfrei.\n\n---\n\n#### 3.2.2 Faraday-Methode\n- Verwendet eine feine Quarzfeder, misst die magnetische Kraft auf mikroskopische Proben.  \n- Sehr präzise, aber zerstörend.  \n- Wird in der Mineralogie genutzt, kaum in der Gemmologie.\n\n---\n\n### 3.3 Hoover Balance – die gemmologische Lösung\n\nDie **Hoover Balance** ist ein spezialisiertes Gerät für die zerstörungsfreie, quantitative Bestimmung der magnetischen Suszeptibilität fester Edelsteine.  \nEntwickelt von **M. Hoover (USA)**, nutzt sie eine Kombination aus Mikrowaage und homogenem Magnetfeld.\n\n#### Funktionsprinzip:\n1. Der Edelstein wird auf eine hochauflösende Waagschale gelegt.  \n2. Ein Magnetfeld wird ein- und ausgeschaltet.  \n3. Die Gewichtsdifferenz (Kraftänderung) wird gemessen.  \n\n\\[\n\\Delta m = k \\cdot \\chi \\cdot H^2\n\\]\n\n(k = Kalibrierfaktor)\n\n#### Vorteile:\n- **Nicht zerstörend**, auch für geschliffene Steine  \n- **Quantitativ und reproduzierbar**  \n- **Hohe Empfindlichkeit** (bis χ ≈ 10⁻⁶)\n\n#### Anwendung:\n- Einsatz in gemmologischen Laboren (z. B. DGemG, GIA, SSEF)  \n- Bestimmung von Fe- oder Mn-Gehalten  \n- Unterscheidung ähnlicher Varietäten (z. B. Pyrop vs. Almandin)\n\n#### Grenzen:\n- Mindestgewicht ~0,5 ct  \n- Notwendige Kalibrierung mit Referenzmaterial  \n- Magnetfeld muss stabil und homogen sein\n\n---\n\n## 4. Edelsteine nach magnetischer Stärke\n\n| Kategorie | Edelstein | Magnetische Reaktion | Hauptursache | χ (ungefähr) |\n|------------|------------|----------------------|---------------|---------------|\n| **Sehr stark** | Magnetit, Hämatit | starke Anziehung, evtl. Hebung | Fe³⁺ | > 10⁻³ |\n| **Stark** | Almandin, Andradit, Spessartin | deutliche Bewegung | Fe²⁺, Mn²⁺ | 10⁻⁴ – 10⁻³ |\n| **Mittel** | Turmalin (Schörl, Dravit), Peridot, Diopsid | leichte Bewegung | Fe, Mn | 10⁻⁵ – 10⁻⁴ |\n| **Schwach** | Aquamarin, Smaragd, Spinell, Saphir (Fe, Ti) | kaum sichtbar | Fe, Cr | 10⁻⁶ – 10⁻⁵ |\n| **Sehr schwach / Diamagnetisch** | Quarz, Topas, Zirkon, Diamant | keine Bewegung / Abstoßung | keine paramagnetischen Ionen | < 10⁻⁶ |\n\n---\n\n## 5. Chemische Ursachen des Magnetismus\n\n| Ion | Elektronenkonfiguration | Wirkung |\n|------|--------------------------|----------|\n| Fe²⁺ | [Ar]3d⁶ | starker Paramagnetismus |\n| Fe³⁺ | [Ar]3d⁵ | mittel bis stark |\n| Mn²⁺ | [Ar]3d⁵ | mittel |\n| Cr³⁺ | [Ar]3d³ | mittel |\n| V³⁺ | [Ar]3d² | schwach |\n| Cu²⁺ | [Ar]3d⁹ | schwach |\n| Ti³⁺ | [Ar]3d¹ | sehr schwach |\n\n---\n\n## 6. Bedeutung in der Edelsteinbestimmung\n\n- **Zerstörungsfreies Verfahren** zur Unterscheidung ähnlicher Varietäten.  \n- **Granate:** starke magnetische Unterschiede – hilfreich für Klassifikation.  \n- **Turmaline:** Schörl > Dravit > Elbait → Varietätenbestimmung.  \n- **Synthetische Korunde:** meist keine magnetische Reaktion → Erkennung möglich.  \n\nIn Kombination mit Refraktometer, Spektroskop und Polarisationsmikroskop bietet Magnetismus eine **zusätzliche physikalische Dimension** der Analyse.\n\n---\n\n## 7. Sicherheitshinweis\n\n- Starke Neodym-Magnete (N52) können Elektronik, Kreditkarten und Armbanduhren beschädigen.  \n- Vorsicht bei Kontakt mit polierten Oberflächen (Kratzergefahr).  \n- Immer Handschuhe oder Kunststoffpinzette verwenden.\n\n---\n\n## 8. Fazit\n\nMagnetismus ist ein **hilfreiches und zunehmend genutztes Kriterium in der modernen Gemmologie**.  \nDurch einfache Tests (Magnet) oder präzise Messungen (Hoover Balance, Guoy) lassen sich wertvolle Informationen über chemische Zusammensetzung und Echtheit gewinnen.  \nInsbesondere Fe- und Mn-haltige Edelsteine zeigen reproduzierbare magnetische Eigenschaften, die eine Zuordnung und Echtheitsprüfung ermöglichen.\n\n---\n\n## 9. Quellen\n\n1. Hoover, M. (2017). *Quantitative Determination of Magnetic Susceptibility in Gemstones*. Hoover Instruments, USA.  \n2. Rossman, G. R. (2018). *Magnetic Properties of Gemstones*. Caltech Mineral Physics Reports.  \n3. Hanneman, H. H. (2011). *Practical Gem Magnetism*, Gems & Gemology.  \n4. Huntsman, O. H. (2019). *Gem Magnetism Database*, GemologyTools.com.  \n5. DGemG Lehrunterlagen (2023). *Physikalische Eigenschaften von Edelsteinen*, Idar-Oberstein.  \n6. Gübelin & Koivula (2016). *Photoatlas of Inclusions in Gemstones*.  \n7. Deer, Howie & Zussman (2020). *Rock-forming Minerals*, Elsevier.",
    "author": "Gemilike Team",
    "category": "Edelsteinkunde",
    "tags": [],
    "image": "/uploads/stories/story-1760126222680.jpg",
    "published": true,
    "featured": false,
    "createdAt": "2025-10-10T19:57:15.547Z",
    "updatedAt": "2025-10-10T19:57:15.547Z",
    "publishedAt": "2025-10-10T19:57:15.547Z"
  },
  {
    "id": "blog_1761046904749_dj55kbivn",
    "title": "das ist ein test",
    "slug": "das-ist-ein-test",
    "excerpt": "Wir testen den blog",
    "content": "![1](/images/stories/placeholder-gem.svg)",
    "author": "Gemilike Team",
    "category": "Investment",
    "tags": [],
    "image": "/images/stories/placeholder-gem.svg",
    "contentImages": [],
    "published": true,
    "featured": false,
    "createdAt": "2025-10-21T11:41:44.749Z",
    "updatedAt": "2025-10-21T11:41:44.749Z",
    "publishedAt": "2025-10-21T11:41:44.749Z"
  }
]